certbot_django/__init__.py
certbot_django/coordinator/__init__.py
certbot_django/coordinator/authenticator.py
certbot_django/coordinator/tests/__init__.py
certbot_django/coordinator/tests/test_authenticator.py
certbot_django/server/__init__.py
certbot_django/server/admin.py
certbot_django/server/apps.py
certbot_django/server/models.py
certbot_django/server/serializers.py
certbot_django/server/urls.py
certbot_django/server/views.py
certbot_django/server/migrations/0001_initial.py
certbot_django/server/migrations/__init__.py
certbot_django/server/templates/certbot_django/detail.html
certbot_django/server/tests/__init__.py
certbot_django/server/tests/test_models.py
certbot_django/server/tests/test_views.py
certbot_django4-0.3.5.dist-info/METADATA
certbot_django4-0.3.5.dist-info/WHEEL
certbot_django4-0.3.5.dist-info/entry_points.txt
certbot_django4-0.3.5.dist-info/top_level.txt
certbot_django4-0.3.5.dist-info/RECORD
